[{"PLAYER_ID": 201589, "SEASON_ID": "2008-09", "LEAGUE_ID": "00", "TEAM_ID": 1610612763, "TEAM_ABBREVIATION": "MEM", "PLAYER_AGE": 21.0, "GP": 76, "GS": 64, "MIN": 19.3, "FGM": 2.5, "FGA": 5.7, "FG_PCT": 0.438, "FG3M": 0.0, "FG3A": 0.0, "FG3_PCT": 0.0, "FTM": 0.5, "FTA": 0.8, "FT_PCT": 0.667, "OREB": 1.4, "DREB": 3.1, "REB": 4.6, "AST": 0.6, "STL": 0.7, "BLK": 0.7, "TOV": 0.6, "PF": 2.7, "PTS": 5.6}, {"PLAYER_ID": 201589, "SEASON_ID": "2009-10", "LEAGUE_ID": "00", "TEAM_ID": 1610612763, "TEAM_ABBREVIATION": "MEM", "PLAYER_AGE": 22.0, "GP": 32, "GS": 1, "MIN": 14.3, "FGM": 2.0, "FGA": 4.6, "FG_PCT": 0.432, "FG3M": 0.0, "FG3A": 0.0, "FG3_PCT": 0.0, "FTM": 0.5, "FTA": 0.9, "FT_PCT": 0.567, "OREB": 1.2, "DREB": 2.3, "REB": 3.4, "AST": 0.5, "STL": 0.4, "BLK": 0.4, "TOV": 0.7, "PF": 1.9, "PTS": 4.5}, {"PLAYER_ID": 201589, "SEASON_ID": "2010-11", "LEAGUE_ID": "00", "TEAM_ID": 1610612763, "TEAM_ABBREVIATION": "MEM", "PLAYER_AGE": 23.0, "GP": 80, "GS": 9, "MIN": 20.1, "FGM": 3.9, "FGA": 7.8, "FG_PCT": 0.497, "FG3M": 0.0, "FG3A": 0.1, "FG3_PCT": 0.0, "FTM": 1.4, "FTA": 1.7, "FT_PCT": 0.813, "OREB": 1.4, "DREB": 2.8, "REB": 4.3, "AST": 0.7, "STL": 0.7, "BLK": 0.8, "TOV": 1.1, "PF": 2.9, "PTS": 9.1}, {"PLAYER_ID": 201589, "SEASON_ID": "2012-13", "LEAGUE_ID": "00", "TEAM_ID": 1610612763, "TEAM_ABBREVIATION": "MEM", "PLAYER_AGE": 25.0, "GP": 59, "GS": 3, "MIN": 16.4, "FGM": 2.7, "FGA": 6.1, "FG_PCT": 0.451, "FG3M": 0.1, "FG3A": 0.3, "FG3_PCT": 0.278, "FTM": 0.6, "FTA": 0.8, "FT_PCT": 0.717, "OREB": 1.2, "DREB": 1.7, "REB": 2.9, "AST": 0.6, "STL": 0.4, "BLK": 0.6, "TOV": 0.7, "PF": 2.1, "PTS": 6.1}, {"PLAYER_ID": 201589, "SEASON_ID": "2013-14", "LEAGUE_ID": "00", "TEAM_ID": 1610612743, "TEAM_ABBREVIATION": "DEN", "PLAYER_AGE": 26.0, "GP": 68, "GS": 1, "MIN": 17.1, "FGM": 2.4, "FGA": 6.0, "FG_PCT": 0.395, "FG3M": 0.4, "FG3A": 0.9, "FG3_PCT": 0.375, "FTM": 0.8, "FTA": 0.9, "FT_PCT": 0.855, "OREB": 0.8, "DREB": 2.3, "REB": 3.1, "AST": 0.9, "STL": 0.6, "BLK": 0.7, "TOV": 0.9, "PF": 2.7, "PTS": 5.9}, {"PLAYER_ID": 201589, "SEASON_ID": "2014-15", "LEAGUE_ID": "00", "TEAM_ID": 1610612743, "TEAM_ABBREVIATION": "DEN", "PLAYER_AGE": 27.0, "GP": 58, "GS": 4, "MIN": 17.0, "FGM": 2.7, "FGA": 6.6, "FG_PCT": 0.404, "FG3M": 0.4, "FG3A": 1.9, "FG3_PCT": 0.236, "FTM": 0.8, "FTA": 1.0, "FT_PCT": 0.78, "OREB": 0.9, "DREB": 2.0, "REB": 2.9, "AST": 1.0, "STL": 0.8, "BLK": 0.4, "TOV": 0.8, "PF": 2.5, "PTS": 6.6}, {"PLAYER_ID": 201589, "SEASON_ID": "2015-16", "LEAGUE_ID": "00", "TEAM_ID": 1610612743, "TEAM_ABBREVIATION": "DEN", "PLAYER_AGE": 28.0, "GP": 70, "GS": 16, "MIN": 21.7, "FGM": 3.2, "FGA": 7.0, "FG_PCT": 0.452, "FG3M": 0.6, "FG3A": 1.7, "FG3_PCT": 0.385, "FTM": 0.6, "FTA": 0.8, "FT_PCT": 0.755, "OREB": 1.2, "DREB": 3.0, "REB": 4.2, "AST": 1.4, "STL": 0.8, "BLK": 0.7, "TOV": 0.9, "PF": 2.6, "PTS": 7.5}, {"PLAYER_ID": 201589, "SEASON_ID": "2016-17", "LEAGUE_ID": "00", "TEAM_ID": 1610612743, "TEAM_ABBREVIATION": "DEN", "PLAYER_AGE": 29.0, "GP": 41, "GS": 7, "MIN": 15.6, "FGM": 2.3, "FGA": 5.2, "FG_PCT": 0.442, "FG3M": 1.3, "FG3A": 2.9, "FG3_PCT": 0.453, "FTM": 0.5, "FTA": 0.5, "FT_PCT": 0.864, "OREB": 0.6, "DREB": 2.1, "REB": 2.7, "AST": 1.0, "STL": 0.5, "BLK": 0.5, "TOV": 0.9, "PF": 1.9, "PTS": 6.4}, {"PLAYER_ID": 201589, "SEASON_ID": "2017-18", "LEAGUE_ID": "00", "TEAM_ID": 1610612743, "TEAM_ABBREVIATION": "DEN", "PLAYER_AGE": 29.0, "GP": 4, "GS": 0, "MIN": 9.6, "FGM": 0.8, "FGA": 3.3, "FG_PCT": 0.231, "FG3M": 0.3, "FG3A": 2.3, "FG3_PCT": 0.111, "FTM": 0.0, "FTA": 0.0, "FT_PCT": 0.0, "OREB": 0.3, "DREB": 1.0, "REB": 1.3, "AST": 0.3, "STL": 0.5, "BLK": 0.0, "TOV": 1.8, "PF": 1.5, "PTS": 1.8}]