{"resource": "boxscore", "parameters": {"GameID": "0021600520", "StartPeriod": 0, "EndPeriod": 0, "StartRange": 0, "EndRange": 0, "RangeType": 0}, "resultSets": [{"name": "PlayerStats", "headers": ["GAME_ID", "TEAM_ID", "TEAM_ABBREVIATION", "TEAM_CITY", "PLAYER_ID", "PLAYER_NAME", "START_POSITION", "COMMENT", "MIN", "FGM", "FGA", "FG_PCT", "FG3M", "FG3A", "FG3_PCT", "FTM", "FTA", "FT_PCT", "OREB", "DREB", "REB", "AST", "STL", "BLK", "TO", "PF", "PTS", "PLUS_MINUS"], "rowSet": [["0021600520", 1610612743, "DEN", "Denver", 201568, "Danilo Gallinari", "F", "", "32:04", 7, 15, 0.467, 2, 7, 0.286, 3, 4, 0.75, 1, 7, 8, 4, 2, 0, 1, 3, 19, -9.0], ["0021600520", 1610612743, "DEN", "Denver", 201163, "Wilson Chandler", "F", "", "37:15", 8, 16, 0.5, 3, 8, 0.375, 2, 3, 0.667, 1, 3, 4, 2, 2, 1, 3, 2, 21, -4.0], ["0021600520", 1610612743, "DEN", "Denver", 203999, "Nikola Jokic", "C", "", "24:48", 8, 17, 0.471, 1, 2, 0.5, 4, 4, 1.0, 8, 5, 13, 5, 1, 0, 2, 2, 21, -5.0], ["0021600520", 1610612743, "DEN", "Denver", 203914, "Gary Harris", "G", "", "31:09", 5, 12, 0.417, 0, 3, 0.0, 1, 2, 0.5, 3, 1, 4, 3, 2, 0, 0, 3, 11, -10.0], ["0021600520", 1610612743, "DEN", "Denver", 1626144, "Emmanuel Mudiay", "G", "", "30:40", 4, 11, 0.364, 0, 3, 0.0, 0, 0, 0.0, 0, 2, 2, 4, 1, 0, 1, 2, 8, -8.0], ["0021600520", 1610612743, "DEN", "Denver", 203115, "Will Barton", "", "", "26:46", 6, 11, 0.545, 2, 5, 0.4, 0, 0, 0.0, 2, 5, 7, 4, 0, 0, 2, 2, 14, 4.0], ["0021600520", 1610612743, "DEN", "Denver", 203994, "Jusuf Nurkic", "", "", "21:07", 6, 8, 0.75, 0, 0, 0.0, 3, 4, 0.75, 0, 6, 6, 4, 1, 1, 1, 3, 15, -4.0], ["0021600520", 1610612743, "DEN", "Denver", 2749, "Jameer Nelson", "", "", "17:20", 2, 4, 0.5, 0, 2, 0.0, 1, 1, 1.0, 0, 0, 0, 4, 0, 0, 4, 4, 5, 0.0], ["0021600520", 1610612743, "DEN", "Denver", 1627750, "Jamal Murray", "", "", "18:51", 2, 7, 0.286, 1, 5, 0.2, 0, 0, 0.0, 1, 3, 4, 3, 1, 0, 0, 0, 5, -4.0], ["0021600520", 1610612743, "DEN", "Denver", 1627736, "Malik Beasley", "", "DNP - Coach's Decision                  ", null, null, null, null, null, null, null, null, null, null, null, null, null, null, null, null, null, null, null, null], ["0021600520", 1610612743, "DEN", "Denver", 202087, "Alonzo Gee", "", "DNP - Coach's Decision                  ", null, null, null, null, null, null, null, null, null, null, null, null, null, null, null, null, null, null, null, null], ["0021600520", 1610612743, "DEN", "Denver", 1627823, "Juan Hernangomez", "", "DNP - Coach's Decision                  ", null, null, null, null, null, null, null, null, null, null, null, null, null, null, null, null, null, null, null, null], ["0021600520", 1610612743, "DEN", "Denver", 2034, "Mike Miller", "", "DNP - Coach's Decision                  ", null, null, null, null, null, null, null, null, null, null, null, null, null, null, null, null, null, null, null, null], ["0021600520", 1610612744, "GSW", "Golden State", 201142, "Kevin Durant", "F", "", "34:27", 10, 19, 0.526, 1, 4, 0.25, 0, 0, 0.0, 0, 3, 3, 2, 1, 1, 2, 2, 21, -4.0], ["0021600520", 1610612744, "GSW", "Golden State", 203110, "Draymond Green", "F", "", "36:05", 5, 8, 0.625, 1, 2, 0.5, 4, 6, 0.667, 3, 7, 10, 13, 0, 0, 5, 3, 15, 11.0], ["0021600520", 1610612744, "GSW", "Golden State", 2585, "Zaza Pachulia", "C", "", "19:26", 4, 8, 0.5, 0, 0, 0.0, 3, 3, 1.0, 4, 5, 9, 1, 0, 0, 2, 4, 11, 17.0], ["0021600520", 1610612744, "GSW", "Golden State", 202691, "Klay Thompson", "G", "", "37:00", 9, 19, 0.474, 4, 7, 0.571, 3, 3, 1.0, 0, 5, 5, 1, 0, 1, 0, 1, 25, 7.0], ["0021600520", 1610612744, "GSW", "Golden State", 201939, "Stephen Curry", "G", "", "35:03", 8, 18, 0.444, 3, 9, 0.333, 3, 3, 1.0, 0, 3, 3, 5, 0, 0, 3, 2, 22, 7.0], ["0021600520", 1610612744, "GSW", "Golden State", 2738, "Andre Iguodala", "", "", "22:12", 2, 4, 0.5, 0, 1, 0.0, 0, 0, 0.0, 1, 2, 3, 3, 2, 0, 1, 0, 4, -10.0], ["0021600520", 1610612744, "GSW", "Golden State", 201580, "JaVale McGee", "", "", "8:59", 4, 4, 1.0, 0, 0, 0.0, 1, 3, 0.333, 1, 3, 4, 0, 1, 0, 0, 0, 9, 0.0], ["0021600520", 1610612744, "GSW", "Golden State", 203546, "Ian Clark", "", "", "15:48", 4, 5, 0.8, 2, 2, 1.0, 2, 2, 1.0, 0, 1, 1, 1, 2, 0, 0, 1, 12, 5.0], ["0021600520", 1610612744, "GSW", "Golden State", 2733, "Shaun Livingston", "", "", "18:18", 3, 6, 0.5, 0, 0, 0.0, 0, 1, 0.0, 2, 1, 3, 4, 1, 0, 0, 0, 6, 9.0], ["0021600520", 1610612744, "GSW", "Golden State", 2561, "David West", "", "", "12:42", 1, 4, 0.25, 0, 0, 0.0, 0, 0, 0.0, 1, 1, 2, 3, 0, 0, 0, 1, 2, -2.0], ["0021600520", 1610612744, "GSW", "Golden State", 1626172, "Kevon Looney", "", "DNP - Coach's Decision                  ", null, null, null, null, null, null, null, null, null, null, null, null, null, null, null, null, null, null, null, null], ["0021600520", 1610612744, "GSW", "Golden State", 203949, "James Michael McAdoo", "", "DNP - Coach's Decision                  ", null, null, null, null, null, null, null, null, null, null, null, null, null, null, null, null, null, null, null, null], ["0021600520", 1610612744, "GSW", "Golden State", 2760, "Anderson Varejao", "", "DNP - Coach's Decision                  ", null, null, null, null, null, null, null, null, null, null, null, null, null, null, null, null, null, null, null, null]]}, {"name": "TeamStats", "headers": ["GAME_ID", "TEAM_ID", "TEAM_NAME", "TEAM_ABBREVIATION", "TEAM_CITY", "MIN", "FGM", "FGA", "FG_PCT", "FG3M", "FG3A", "FG3_PCT", "FTM", "FTA", "FT_PCT", "OREB", "DREB", "REB", "AST", "STL", "BLK", "TO", "PF", "PTS", "PLUS_MINUS"], "rowSet": [["0021600520", 1610612744, "Warriors", "GSW", "Golden State", "240:00", 50, 95, 0.526, 11, 25, 0.44, 16, 21, 0.762, 12, 31, 43, 33, 7, 2, 13, 14, 127, 8.0], ["0021600520", 1610612743, "Nuggets", "DEN", "Denver", "240:00", 48, 101, 0.475, 9, 35, 0.257, 14, 18, 0.778, 16, 32, 48, 33, 10, 2, 14, 21, 119, -8.0]]}, {"name": "TeamStarterBenchStats", "headers": ["GAME_ID", "TEAM_ID", "TEAM_NAME", "TEAM_ABBREVIATION", "TEAM_CITY", "STARTERS_BENCH", "MIN", "FGM", "FGA", "FG_PCT", "FG3M", "FG3A", "FG3_PCT", "FTM", "FTA", "FT_PCT", "OREB", "DREB", "REB", "AST", "STL", "BLK", "TO", "PF", "PTS"], "rowSet": [["0021600520", 1610612744, "Warriors", "GSW", "Golden State", "Starters", "162:01", 36, 72, 0.5, 9, 22, 0.409, 13, 15, 0.867, 7, 23, 30, 22, 1, 2, 12, 12, 94], ["0021600520", 1610612744, "Warriors", "GSW", "Golden State", "Bench", "69:00", 10, 19, 0.526, 2, 3, 0.667, 2, 3, 0.667, 4, 5, 9, 11, 5, 0, 1, 2, 24], ["0021600520", 1610612743, "Nuggets", "DEN", "Denver", "Starters", "155:56", 32, 71, 0.451, 6, 23, 0.261, 10, 13, 0.769, 13, 18, 31, 18, 8, 1, 7, 12, 80], ["0021600520", 1610612743, "Nuggets", "DEN", "Denver", "Bench", "84:04", 16, 30, 0.533, 3, 12, 0.25, 4, 5, 0.8, 3, 14, 17, 15, 2, 1, 7, 9, 39]]}]}