{"resource": "boxscore", "parameters": {"GameID": "0021601079", "StartPeriod": 0, "EndPeriod": 0, "StartRange": 0, "EndRange": 0, "RangeType": 0}, "resultSets": [{"name": "PlayerStats", "headers": ["GAME_ID", "TEAM_ID", "TEAM_ABBREVIATION", "TEAM_CITY", "PLAYER_ID", "PLAYER_NAME", "START_POSITION", "COMMENT", "MIN", "FGM", "FGA", "FG_PCT", "FG3M", "FG3A", "FG3_PCT", "FTM", "FTA", "FT_PCT", "OREB", "DREB", "REB", "AST", "STL", "BLK", "TO", "PF", "PTS", "PLUS_MINUS"], "rowSet": [["0021601079", 1610612740, "NOP", "New Orleans", 203524, "Solomon Hill", "F", "", "36:00", 3, 8, 0.375, 3, 7, 0.429, 0, 0, 0.0, 0, 3, 3, 4, 1, 0, 2, 3, 9, -3.0], ["0021601079", 1610612740, "NOP", "New Orleans", 203076, "Anthony Davis", "F", "", "40:52", 14, 24, 0.583, 0, 1, 0.0, 5, 6, 0.833, 3, 13, 16, 1, 3, 1, 1, 2, 33, -9.0], ["0021601079", 1610612740, "NOP", "New Orleans", 202326, "DeMarcus Cousins", "C", "", "29:52", 10, 25, 0.4, 5, 9, 0.556, 4, 5, 0.8, 2, 4, 6, 4, 1, 4, 3, 4, 29, -8.0], ["0021601079", 1610612740, "NOP", "New Orleans", 201950, "Jrue Holiday", "G", "", "38:22", 7, 12, 0.583, 4, 8, 0.5, 0, 1, 0.0, 0, 1, 1, 9, 3, 2, 2, 1, 18, -7.0], ["0021601079", 1610612740, "NOP", "New Orleans", 204025, "Tim Frazier", "G", "", "24:20", 0, 5, 0.0, 0, 4, 0.0, 0, 0, 0.0, 0, 3, 3, 3, 0, 0, 0, 1, 0, 0.0], ["0021601079", 1610612740, "NOP", "New Orleans", 202734, "E'Twaun Moore", "", "", "27:18", 3, 6, 0.5, 0, 2, 0.0, 0, 0, 0.0, 1, 1, 2, 5, 0, 0, 0, 3, 6, -10.0], ["0021601079", 1610612740, "NOP", "New Orleans", 201967, "Dante Cunningham", "", "", "24:58", 0, 1, 0.0, 0, 1, 0.0, 0, 0, 0.0, 0, 4, 4, 0, 0, 0, 0, 1, 0, -3.0], ["0021601079", 1610612740, "NOP", "New Orleans", 202348, "Jordan Crawford", "", "", "18:18", 4, 10, 0.4, 2, 6, 0.333, 2, 2, 1.0, 0, 1, 1, 2, 1, 0, 2, 0, 12, -10.0], ["0021601079", 1610612740, "NOP", "New Orleans", 201582, "Alexis Ajinca", "", "DNP - Coach's Decision                  ", null, null, null, null, null, null, null, null, null, null, null, null, null, null, null, null, null, null, null, null], ["0021601079", 1610612740, "NOP", "New Orleans", 201600, "Omer Asik", "", "NWT - Illness                           ", null, null, null, null, null, null, null, null, null, null, null, null, null, null, null, null, null, null, null, null], ["0021601079", 1610612740, "NOP", "New Orleans", 1626188, "Quinn Cook", "", "DNP - Coach's Decision                  ", null, null, null, null, null, null, null, null, null, null, null, null, null, null, null, null, null, null, null, null], ["0021601079", 1610612740, "NOP", "New Orleans", 202700, "Donatas Motiejunas", "", "DNP - Coach's Decision                  ", null, null, null, null, null, null, null, null, null, null, null, null, null, null, null, null, null, null, null, null], ["0021601079", 1610612745, "HOU", "Houston", 2772, "Trevor Ariza", "F", "", "33:50", 3, 10, 0.3, 0, 4, 0.0, 2, 2, 1.0, 0, 9, 9, 0, 0, 0, 0, 4, 8, 8.0], ["0021601079", 1610612745, "HOU", "Houston", 201583, "Ryan Anderson", "F", "", "29:59", 5, 12, 0.417, 3, 8, 0.375, 0, 0, 0.0, 4, 2, 6, 0, 0, 0, 2, 3, 13, 8.0], ["0021601079", 1610612745, "HOU", "Houston", 203991, "Clint Capela", "C", "", "28:35", 5, 7, 0.714, 0, 0, 0.0, 0, 0, 0.0, 4, 9, 13, 2, 0, 2, 2, 3, 10, 20.0], ["0021601079", 1610612745, "HOU", "Houston", 201976, "Patrick Beverley", "G", "", "31:25", 6, 11, 0.545, 4, 7, 0.571, 1, 2, 0.5, 1, 5, 6, 2, 1, 0, 4, 2, 17, 2.0], ["0021601079", 1610612745, "HOU", "Houston", 201935, "James Harden", "G", "", "37:45", 12, 24, 0.5, 5, 12, 0.417, 9, 11, 0.818, 1, 6, 7, 17, 2, 1, 3, 2, 38, 12.0], ["0021601079", 1610612745, "HOU", "Houston", 2403, "Nene", "", "", "19:25", 6, 10, 0.6, 0, 0, 0.0, 0, 0, 0.0, 2, 6, 8, 2, 1, 0, 1, 4, 12, -10.0], ["0021601079", 1610612745, "HOU", "Houston", 201569, "Eric Gordon", "", "", "33:04", 5, 10, 0.5, 2, 5, 0.4, 2, 3, 0.667, 1, 4, 5, 4, 1, 0, 5, 1, 14, 16.0], ["0021601079", 1610612745, "HOU", "Houston", 101150, "Lou Williams", "", "", "19:33", 2, 8, 0.25, 0, 3, 0.0, 1, 2, 0.5, 1, 1, 2, 2, 0, 0, 1, 0, 5, -2.0], ["0021601079", 1610612745, "HOU", "Houston", 1626155, "Sam Dekker", "", "", "6:24", 0, 1, 0.0, 0, 0, 0.0, 0, 0, 0.0, 1, 2, 3, 0, 0, 0, 0, 0, 0, -4.0], ["0021601079", 1610612745, "HOU", "Houston", 201628, "Bobby Brown", "", "DNP - Coach's Decision                  ", null, null, null, null, null, null, null, null, null, null, null, null, null, null, null, null, null, null, null, null], ["0021601079", 1610612745, "HOU", "Houston", 1626149, "Montrezl Harrell", "", "DNP - Coach's Decision                  ", null, null, null, null, null, null, null, null, null, null, null, null, null, null, null, null, null, null, null, null], ["0021601079", 1610612745, "HOU", "Houston", 1627787, "Kyle Wiltjer", "", "DNP - Coach's Decision                  ", null, null, null, null, null, null, null, null, null, null, null, null, null, null, null, null, null, null, null, null]]}, {"name": "TeamStats", "headers": ["GAME_ID", "TEAM_ID", "TEAM_NAME", "TEAM_ABBREVIATION", "TEAM_CITY", "MIN", "FGM", "FGA", "FG_PCT", "FG3M", "FG3A", "FG3_PCT", "FTM", "FTA", "FT_PCT", "OREB", "DREB", "REB", "AST", "STL", "BLK", "TO", "PF", "PTS", "PLUS_MINUS"], "rowSet": [["0021601079", 1610612740, "Pelicans", "NOP", "New Orleans", "240:00", 41, 91, 0.451, 14, 38, 0.368, 11, 14, 0.786, 6, 30, 36, 28, 9, 7, 10, 15, 107, -10.0], ["0021601079", 1610612745, "Rockets", "HOU", "Houston", "240:00", 44, 93, 0.473, 14, 39, 0.359, 15, 20, 0.75, 15, 44, 59, 29, 5, 3, 18, 19, 117, 10.0]]}, {"name": "TeamStarterBenchStats", "headers": ["GAME_ID", "TEAM_ID", "TEAM_NAME", "TEAM_ABBREVIATION", "TEAM_CITY", "STARTERS_BENCH", "MIN", "FGM", "FGA", "FG_PCT", "FG3M", "FG3A", "FG3_PCT", "FTM", "FTA", "FT_PCT", "OREB", "DREB", "REB", "AST", "STL", "BLK", "TO", "PF", "PTS"], "rowSet": [["0021601079", 1610612740, "Pelicans", "NOP", "New Orleans", "Starters", "169:26", 34, 74, 0.459, 12, 29, 0.414, 9, 12, 0.75, 5, 24, 29, 21, 8, 7, 8, 11, 89], ["0021601079", 1610612740, "Pelicans", "NOP", "New Orleans", "Bench", "70:34", 7, 17, 0.412, 2, 9, 0.222, 2, 2, 1.0, 1, 6, 7, 7, 1, 0, 2, 4, 18], ["0021601079", 1610612745, "Rockets", "HOU", "Houston", "Starters", "161:34", 31, 64, 0.484, 12, 31, 0.387, 12, 15, 0.8, 10, 31, 41, 21, 3, 3, 11, 14, 86], ["0021601079", 1610612745, "Rockets", "HOU", "Houston", "Bench", "59:01", 7, 19, 0.368, 2, 8, 0.25, 3, 5, 0.6, 3, 7, 10, 6, 1, 0, 6, 1, 19]]}]}