{"resource": "boxscore", "parameters": {"GameID": "0021600758", "StartPeriod": 0, "EndPeriod": 0, "StartRange": 0, "EndRange": 0, "RangeType": 0}, "resultSets": [{"name": "PlayerStats", "headers": ["GAME_ID", "TEAM_ID", "TEAM_ABBREVIATION", "TEAM_CITY", "PLAYER_ID", "PLAYER_NAME", "START_POSITION", "COMMENT", "MIN", "FGM", "FGA", "FG_PCT", "FG3M", "FG3A", "FG3_PCT", "FTM", "FTA", "FT_PCT", "OREB", "DREB", "REB", "AST", "STL", "BLK", "TO", "PF", "PTS", "PLUS_MINUS"], "rowSet": [["0021600758", 1610612755, "PHI", "Philadelphia", 203917, "Nik Stauskas", "F", "", "39:52", 2, 11, 0.182, 0, 4, 0.0, 4, 4, 1.0, 0, 4, 4, 6, 2, 0, 2, 3, 8, -20.0], ["0021600758", 1610612755, "PHI", "Philadelphia", 101141, "Ersan Ilyasova", "F", "", "26:32", 7, 15, 0.467, 3, 7, 0.429, 4, 5, 0.8, 1, 4, 5, 2, 0, 0, 2, 1, 21, -15.0], ["0021600758", 1610612755, "PHI", "Philadelphia", 203457, "Nerlens Noel", "C", "", "19:46", 2, 6, 0.333, 0, 0, 0.0, 3, 4, 0.75, 1, 6, 7, 2, 2, 0, 1, 2, 7, -15.0], ["0021600758", 1610612755, "PHI", "Philadelphia", 201945, "Gerald Henderson", "G", "", "24:31", 6, 12, 0.5, 0, 0, 0.0, 0, 0, 0.0, 0, 0, 0, 2, 2, 0, 0, 2, 12, -14.0], ["0021600758", 1610612755, "PHI", "Philadelphia", 204456, "T.J. McConnell", "G", "", "28:16", 5, 6, 0.833, 0, 0, 0.0, 1, 1, 1.0, 0, 2, 2, 4, 0, 0, 4, 3, 11, -21.0], ["0021600758", 1610612755, "PHI", "Philadelphia", 1626158, "Richaun Holmes", "", "", "24:01", 4, 6, 0.667, 0, 0, 0.0, 4, 4, 1.0, 2, 7, 9, 2, 1, 0, 2, 2, 12, -4.0], ["0021600758", 1610612755, "PHI", "Philadelphia", 203967, "Dario Saric", "", "", "26:47", 1, 9, 0.111, 0, 3, 0.0, 2, 4, 0.5, 1, 3, 4, 0, 2, 0, 2, 4, 4, -9.0], ["0021600758", 1610612755, "PHI", "Philadelphia", 200771, "Sergio Rodriguez", "", "", "12:14", 4, 7, 0.571, 2, 2, 1.0, 0, 0, 0.0, 0, 1, 1, 1, 0, 0, 2, 1, 10, -11.0], ["0021600758", 1610612755, "PHI", "Philadelphia", 1627789, "Timothe Luwawu-Cabarrot", "", "", "25:38", 3, 8, 0.375, 1, 4, 0.25, 2, 3, 0.667, 1, 0, 1, 0, 1, 1, 0, 2, 9, -10.0], ["0021600758", 1610612755, "PHI", "Philadelphia", 1626184, "Chasson Randle", "", "", "12:23", 1, 4, 0.25, 0, 3, 0.0, 6, 6, 1.0, 0, 0, 0, 1, 0, 0, 0, 1, 8, 4.0], ["0021600758", 1610612755, "PHI", "Philadelphia", 203496, "Robert Covington", "", "DND - Right Hand Contusion              ", null, null, null, null, null, null, null, null, null, null, null, null, null, null, null, null, null, null, null, null], ["0021600758", 1610612755, "PHI", "Philadelphia", 203954, "Joel Embiid", "", "NWT - Left Knee Soreness                ", null, null, null, null, null, null, null, null, null, null, null, null, null, null, null, null, null, null, null, null], ["0021600758", 1610612755, "PHI", "Philadelphia", 1626143, "Jahlil Okafor", "", "DNP - Coach's Decision                  ", null, null, null, null, null, null, null, null, null, null, null, null, null, null, null, null, null, null, null, null], ["0021600758", 1610612748, "MIA", "Miami", 203585, "Rodney McGruder", "F", "", "15:25", 0, 2, 0.0, 0, 1, 0.0, 0, 2, 0.0, 0, 0, 0, 1, 0, 0, 2, 0, 0, 11.0], ["0021600758", 1610612748, "MIA", "Miami", 202337, "Luke Babbitt", "F", "", "24:45", 2, 5, 0.4, 2, 4, 0.5, 2, 2, 1.0, 0, 1, 1, 1, 0, 0, 1, 4, 8, 17.0], ["0021600758", 1610612748, "MIA", "Miami", 202355, "Hassan Whiteside", "C", "", "26:47", 14, 17, 0.824, 0, 0, 0.0, 2, 3, 0.667, 6, 14, 20, 0, 0, 3, 3, 1, 30, 24.0], ["0021600758", 1610612748, "MIA", "Miami", 203079, "Dion Waiters", "G", "", "26:15", 7, 10, 0.7, 5, 6, 0.833, 2, 2, 1.0, 0, 1, 1, 7, 2, 1, 3, 0, 21, 30.0], ["0021600758", 1610612748, "MIA", "Miami", 201609, "Goran Dragic", "G", "", "27:58", 6, 11, 0.545, 2, 2, 1.0, 2, 3, 0.667, 0, 4, 4, 8, 0, 0, 1, 3, 16, 16.0], ["0021600758", 1610612748, "MIA", "Miami", 204020, "Tyler Johnson", "", "", "33:46", 5, 9, 0.556, 0, 0, 0.0, 6, 8, 0.75, 0, 6, 6, 6, 1, 1, 2, 4, 16, 9.0], ["0021600758", 1610612748, "MIA", "Miami", 201949, "James Johnson", "", "", "15:33", 4, 5, 0.8, 0, 1, 0.0, 2, 2, 1.0, 0, 6, 6, 3, 2, 0, 1, 2, 10, 8.0], ["0021600758", 1610612748, "MIA", "Miami", 201961, "Wayne Ellington", "", "", "15:58", 4, 7, 0.571, 2, 4, 0.5, 1, 1, 1.0, 1, 1, 2, 0, 1, 0, 3, 5, 11, 7.0], ["0021600758", 1610612748, "MIA", "Miami", 203186, "Willie Reed", "", "", "13:52", 1, 4, 0.25, 0, 0, 0.0, 0, 0, 0.0, 1, 0, 1, 0, 0, 0, 1, 1, 2, 6.0], ["0021600758", 1610612748, "MIA", "Miami", 1627855, "Okaro White", "", "", "24:33", 2, 6, 0.333, 1, 2, 0.5, 0, 0, 0.0, 1, 2, 3, 2, 0, 0, 2, 1, 5, 0.0], ["0021600758", 1610612748, "MIA", "Miami", 202682, "Derrick Williams", "", "", "7:47", 1, 2, 0.5, 0, 1, 0.0, 0, 0, 0.0, 0, 1, 1, 0, 0, 0, 2, 2, 2, -6.0], ["0021600758", 1610612748, "MIA", "Miami", 2617, "Udonis Haslem", "", "", "7:21", 2, 4, 0.5, 0, 1, 0.0, 0, 0, 0.0, 1, 3, 4, 0, 0, 0, 0, 1, 4, -7.0], ["0021600758", 1610612748, "MIA", "Miami", 1626196, "Josh Richardson", "", "DND - Left Foot Sprain                  ", null, null, null, null, null, null, null, null, null, null, null, null, null, null, null, null, null, null, null, null]]}, {"name": "TeamStats", "headers": ["GAME_ID", "TEAM_ID", "TEAM_NAME", "TEAM_ABBREVIATION", "TEAM_CITY", "MIN", "FGM", "FGA", "FG_PCT", "FG3M", "FG3A", "FG3_PCT", "FTM", "FTA", "FT_PCT", "OREB", "DREB", "REB", "AST", "STL", "BLK", "TO", "PF", "PTS", "PLUS_MINUS"], "rowSet": [["0021600758", 1610612755, "76ers", "PHI", "Philadelphia", "240:00", 35, 84, 0.417, 6, 23, 0.261, 26, 31, 0.839, 6, 27, 33, 20, 10, 1, 15, 21, 102, -23.0], ["0021600758", 1610612748, "Heat", "MIA", "Miami", "240:00", 48, 82, 0.585, 12, 22, 0.545, 17, 23, 0.739, 10, 39, 49, 28, 6, 5, 21, 24, 125, 23.0]]}, {"name": "TeamStarterBenchStats", "headers": ["GAME_ID", "TEAM_ID", "TEAM_NAME", "TEAM_ABBREVIATION", "TEAM_CITY", "STARTERS_BENCH", "MIN", "FGM", "FGA", "FG_PCT", "FG3M", "FG3A", "FG3_PCT", "FTM", "FTA", "FT_PCT", "OREB", "DREB", "REB", "AST", "STL", "BLK", "TO", "PF", "PTS"], "rowSet": [["0021600758", 1610612755, "76ers", "PHI", "Philadelphia", "Starters", "138:57", 22, 50, 0.44, 3, 11, 0.273, 12, 14, 0.857, 2, 16, 18, 16, 6, 0, 9, 11, 59], ["0021600758", 1610612755, "76ers", "PHI", "Philadelphia", "Bench", "77:02", 9, 28, 0.321, 3, 12, 0.25, 10, 13, 0.769, 2, 4, 6, 2, 3, 1, 4, 8, 31], ["0021600758", 1610612748, "Heat", "MIA", "Miami", "Starters", "121:10", 29, 45, 0.644, 9, 13, 0.692, 8, 12, 0.667, 6, 20, 26, 17, 2, 4, 10, 8, 75], ["0021600758", 1610612748, "Heat", "MIA", "Miami", "Bench", "118:50", 19, 37, 0.514, 3, 9, 0.333, 9, 11, 0.818, 4, 19, 23, 11, 4, 1, 11, 16, 50]]}]}